{
  "db_name": "PostgreSQL",
  "query": "SELECT task_id, name, priority FROM tasks WHERE task_id = $1",
  "describe": {
    "columns": [
      {
        "ordinal": 0,
        "name": "task_id",
        "type_info": "Int4"
      },
      {
        "ordinal": 1,
        "name": "name",
        "type_info": "Varchar"
      },
      {
        "ordinal": 2,
        "name": "priority",
        "type_info": "Int4"
      }
    ],
    "parameters": {
      "Left": [
        "Int4"
      ]
    },
    "nullable": [
      false,
      false,
      true
    ]
  },
  "hash": "7d99947513c9f69d3ba0301e6220b5e3ae52f8cdf51fe645db3a3ccef93b05b1"
}
